caronte_common/__init__.py
caronte_common/dto/__init__.py
caronte_common/dto/claim.py
caronte_common/dto/config.py
caronte_common/dto/db_document.py
caronte_common/dto/owner.py
caronte_common/dto/project.py
caronte_common/dto/role.py
caronte_common/dto/user.py
caronte_common/interfaces/__init__.py
caronte_common/interfaces/command.py
caronte_common/interfaces/factory.py
caronte_common/utils/singleton.py
caronte_api_common-1.1.0.dist-info/LICENSE
caronte_api_common-1.1.0.dist-info/METADATA
caronte_api_common-1.1.0.dist-info/WHEEL
caronte_api_common-1.1.0.dist-info/RECORD
