Metadata-Version: 2.1
Name: caronte-api-common
Version: 1.1.0
Summary: Common components and modules to integrate Caronte layers
License: GNU
Author: Giovani Liskoski Zanini
Author-email: giovanilzanini@hotmail.com
Requires-Python: >=3.9,<4.0
Classifier: License :: Other/Proprietary License
Classifier: Programming Language :: Python :: 3
Classifier: Programming Language :: Python :: 3.9
Classifier: Programming Language :: Python :: 3.10
Classifier: Programming Language :: Python :: 3.11
Requires-Dist: email-validator (>=1.3.0,<2.0.0)
Requires-Dist: pydantic (>=1.10.4,<2.0.0)
